{
  "datasets": [
    {
      "name": "dataset1",
      "displayName": "silver_movies",
      "queryLines": [
        "SELECT * FROM usa.movies.silver_movies"
      ]
    },
    {
      "name": "8daeeada",
      "displayName": "bronze_mongodb_movies",
      "queryLines": [
        "SELECT * FROM usa.movies.bronze_mongodb_movies;"
      ]
    },
    {
      "name": "d04ce6d0",
      "displayName": "bronze_imdb_movies",
      "queryLines": [
        "SELECT * FROM usa.movies.bronze_imdb_movies;"
      ]
    },
    {
      "name": "3d31630a",
      "displayName": "Top 10 Genres",
      "queryLines": [
        "SELECT *\n",
        "FROM usa.movies.gold_genre_analysis"
      ]
    }
  ],
  "pages": [
    {
      "name": "0641fbdf",
      "displayName": "Top 10 Genres",
      "layout": [
        {
          "widget": {
            "name": "04067e65",
            "queries": [
              {
                "name": "main_query",
                "query": {
                  "datasetName": "3d31630a",
                  "fields": [
                    {
                      "name": "sum",
                      "expression": "`sum`"
                    },
                    {
                      "name": "genre",
                      "expression": "`genre`"
                    }
                  ],
                  "disaggregated": true
                }
              }
            ],
            "spec": {
              "version": 3,
              "widgetType": "pie",
              "encodings": {
                "angle": {
                  "fieldName": "sum",
                  "scale": {
                    "type": "quantitative"
                  },
                  "displayName": "sum"
                },
                "color": {
                  "fieldName": "genre",
                  "scale": {
                    "type": "categorical"
                  },
                  "displayName": "genre"
                },
                "label": {
                  "show": true
                },
                "extra": [
                  {
                    "fieldName": "genre",
                    "displayName": "genre"
                  }
                ]
              }
            }
          },
          "position": {
            "x": 0,
            "y": 0,
            "width": 5,
            "height": 8
          }
        }
      ],
      "pageType": "PAGE_TYPE_CANVAS"
    },
    {
      "name": "page1",
      "displayName": "Silver",
      "layout": [
        {
          "widget": {
            "name": "bar_chart1",
            "queries": [
              {
                "name": "main_query",
                "query": {
                  "datasetName": "dataset1",
                  "fields": [
                    {
                      "name": "count(id)",
                      "expression": "COUNT(`id`)"
                    }
                  ],
                  "disaggregated": false
                }
              }
            ],
            "spec": {
              "version": 2,
              "widgetType": "counter",
              "encodings": {
                "value": {
                  "fieldName": "count(id)",
                  "format": {
                    "type": "number-plain",
                    "abbreviation": "none",
                    "decimalPlaces": {
                      "type": "max",
                      "places": 2
                    }
                  },
                  "displayName": "Count of id"
                }
              },
              "frame": {
                "title": "total",
                "showTitle": true
              }
            }
          },
          "position": {
            "x": 0,
            "y": 0,
            "width": 1,
            "height": 2
          }
        },
        {
          "widget": {
            "name": "table1",
            "queries": [
              {
                "name": "main_query",
                "query": {
                  "datasetName": "dataset1",
                  "fields": [
                    {
                      "name": "source",
                      "expression": "`source`"
                    },
                    {
                      "name": "id",
                      "expression": "`id`"
                    },
                    {
                      "name": "wallTime",
                      "expression": "`wallTime`"
                    },
                    {
                      "name": "title",
                      "expression": "`title`"
                    },
                    {
                      "name": "genres",
                      "expression": "`genres`"
                    },
                    {
                      "name": "year",
                      "expression": "`year`"
                    },
                    {
                      "name": "operationType",
                      "expression": "`operationType`"
                    }
                  ],
                  "disaggregated": true
                }
              }
            ],
            "spec": {
              "version": 1,
              "widgetType": "table",
              "encodings": {
                "columns": [
                  {
                    "fieldName": "source",
                    "booleanValues": [
                      "false",
                      "true"
                    ],
                    "imageUrlTemplate": "{{ @ }}",
                    "imageTitleTemplate": "{{ @ }}",
                    "imageWidth": "",
                    "imageHeight": "",
                    "linkUrlTemplate": "{{ @ }}",
                    "linkTextTemplate": "{{ @ }}",
                    "linkTitleTemplate": "{{ @ }}",
                    "linkOpenInNewTab": true,
                    "type": "string",
                    "displayAs": "string",
                    "visible": true,
                    "order": 0,
                    "title": "source",
                    "allowSearch": false,
                    "alignContent": "left",
                    "allowHTML": false,
                    "highlightLinks": false,
                    "useMonospaceFont": false,
                    "preserveWhitespace": false,
                    "displayName": "source"
                  },
                  {
                    "fieldName": "id",
                    "numberFormat": "0",
                    "booleanValues": [
                      "false",
                      "true"
                    ],
                    "imageUrlTemplate": "{{ @ }}",
                    "imageTitleTemplate": "{{ @ }}",
                    "imageWidth": "",
                    "imageHeight": "",
                    "linkUrlTemplate": "{{ @ }}",
                    "linkTextTemplate": "{{ @ }}",
                    "linkTitleTemplate": "{{ @ }}",
                    "linkOpenInNewTab": true,
                    "type": "integer",
                    "displayAs": "number",
                    "visible": true,
                    "order": 1,
                    "title": "id",
                    "allowSearch": false,
                    "alignContent": "right",
                    "allowHTML": false,
                    "highlightLinks": false,
                    "useMonospaceFont": false,
                    "preserveWhitespace": false,
                    "displayName": "id"
                  },
                  {
                    "fieldName": "wallTime",
                    "dateTimeFormat": "DD/MM/YYYY HH:mm:ss.SSS",
                    "booleanValues": [
                      "false",
                      "true"
                    ],
                    "imageUrlTemplate": "{{ @ }}",
                    "imageTitleTemplate": "{{ @ }}",
                    "imageWidth": "",
                    "imageHeight": "",
                    "linkUrlTemplate": "{{ @ }}",
                    "linkTextTemplate": "{{ @ }}",
                    "linkTitleTemplate": "{{ @ }}",
                    "linkOpenInNewTab": true,
                    "type": "datetime",
                    "displayAs": "datetime",
                    "visible": true,
                    "order": 2,
                    "title": "wallTime",
                    "allowSearch": false,
                    "alignContent": "right",
                    "allowHTML": false,
                    "highlightLinks": false,
                    "useMonospaceFont": false,
                    "preserveWhitespace": false,
                    "displayName": "wallTime"
                  },
                  {
                    "fieldName": "title",
                    "booleanValues": [
                      "false",
                      "true"
                    ],
                    "imageUrlTemplate": "{{ @ }}",
                    "imageTitleTemplate": "{{ @ }}",
                    "imageWidth": "",
                    "imageHeight": "",
                    "linkUrlTemplate": "{{ @ }}",
                    "linkTextTemplate": "{{ @ }}",
                    "linkTitleTemplate": "{{ @ }}",
                    "linkOpenInNewTab": true,
                    "type": "string",
                    "displayAs": "string",
                    "visible": true,
                    "order": 3,
                    "title": "title",
                    "allowSearch": false,
                    "alignContent": "left",
                    "allowHTML": false,
                    "highlightLinks": false,
                    "useMonospaceFont": false,
                    "preserveWhitespace": false,
                    "displayName": "title"
                  },
                  {
                    "fieldName": "genres",
                    "booleanValues": [
                      "false",
                      "true"
                    ],
                    "imageUrlTemplate": "{{ @ }}",
                    "imageTitleTemplate": "{{ @ }}",
                    "imageWidth": "",
                    "imageHeight": "",
                    "linkUrlTemplate": "{{ @ }}",
                    "linkTextTemplate": "{{ @ }}",
                    "linkTitleTemplate": "{{ @ }}",
                    "linkOpenInNewTab": true,
                    "type": "complex",
                    "displayAs": "json",
                    "visible": true,
                    "order": 4,
                    "title": "genres",
                    "allowSearch": false,
                    "alignContent": "left",
                    "allowHTML": false,
                    "highlightLinks": false,
                    "useMonospaceFont": false,
                    "preserveWhitespace": false,
                    "displayName": "genres"
                  },
                  {
                    "fieldName": "year",
                    "booleanValues": [
                      "false",
                      "true"
                    ],
                    "imageUrlTemplate": "{{ @ }}",
                    "imageTitleTemplate": "{{ @ }}",
                    "imageWidth": "",
                    "imageHeight": "",
                    "linkUrlTemplate": "{{ @ }}",
                    "linkTextTemplate": "{{ @ }}",
                    "linkTitleTemplate": "{{ @ }}",
                    "linkOpenInNewTab": true,
                    "type": "string",
                    "displayAs": "string",
                    "visible": true,
                    "order": 5,
                    "title": "year",
                    "allowSearch": false,
                    "alignContent": "left",
                    "allowHTML": false,
                    "highlightLinks": false,
                    "useMonospaceFont": false,
                    "preserveWhitespace": false,
                    "displayName": "year"
                  },
                  {
                    "fieldName": "operationType",
                    "booleanValues": [
                      "false",
                      "true"
                    ],
                    "imageUrlTemplate": "{{ @ }}",
                    "imageTitleTemplate": "{{ @ }}",
                    "imageWidth": "",
                    "imageHeight": "",
                    "linkUrlTemplate": "{{ @ }}",
                    "linkTextTemplate": "{{ @ }}",
                    "linkTitleTemplate": "{{ @ }}",
                    "linkOpenInNewTab": true,
                    "type": "string",
                    "displayAs": "string",
                    "visible": true,
                    "order": 6,
                    "title": "operationType",
                    "allowSearch": false,
                    "alignContent": "left",
                    "allowHTML": false,
                    "highlightLinks": false,
                    "useMonospaceFont": false,
                    "preserveWhitespace": false,
                    "displayName": "operationType"
                  }
                ]
              },
              "invisibleColumns": [],
              "allowHTMLByDefault": false,
              "itemsPerPage": 25,
              "paginationSize": "default",
              "condensed": true,
              "withRowNumber": false
            }
          },
          "position": {
            "x": 0,
            "y": 2,
            "width": 6,
            "height": 6
          }
        },
        {
          "widget": {
            "name": "2acafeb5",
            "queries": [
              {
                "name": "main_query",
                "query": {
                  "datasetName": "dataset1",
                  "fields": [
                    {
                      "name": "count(id)",
                      "expression": "COUNT(`id`)"
                    }
                  ],
                  "filters": [
                    {
                      "expression": "`source` IN ('IMDb Non-Commercial Datasets')"
                    }
                  ],
                  "disaggregated": false
                }
              }
            ],
            "spec": {
              "version": 2,
              "widgetType": "counter",
              "encodings": {
                "value": {
                  "fieldName": "count(id)",
                  "format": {
                    "type": "number-plain",
                    "abbreviation": "none",
                    "decimalPlaces": {
                      "type": "max",
                      "places": 2
                    }
                  },
                  "displayName": "Count of id"
                }
              },
              "frame": {
                "title": "imdb",
                "showTitle": true
              }
            }
          },
          "position": {
            "x": 1,
            "y": 0,
            "width": 1,
            "height": 2
          }
        },
        {
          "widget": {
            "name": "8a1c41ae",
            "queries": [
              {
                "name": "main_query",
                "query": {
                  "datasetName": "dataset1",
                  "fields": [
                    {
                      "name": "count(id)",
                      "expression": "COUNT(`id`)"
                    }
                  ],
                  "filters": [
                    {
                      "expression": "`source` IN ('mongodb_sample_mflix')"
                    }
                  ],
                  "disaggregated": false
                }
              }
            ],
            "spec": {
              "version": 2,
              "widgetType": "counter",
              "encodings": {
                "value": {
                  "fieldName": "count(id)",
                  "format": {
                    "type": "number-plain",
                    "abbreviation": "none",
                    "decimalPlaces": {
                      "type": "max",
                      "places": 2
                    }
                  },
                  "displayName": "Count of id"
                }
              },
              "frame": {
                "title": "mongodb",
                "showTitle": true
              }
            }
          },
          "position": {
            "x": 2,
            "y": 0,
            "width": 1,
            "height": 2
          }
        }
      ],
      "pageType": "PAGE_TYPE_CANVAS"
    },
    {
      "name": "5302363b",
      "displayName": "Bronze - mongodb",
      "layout": [
        {
          "widget": {
            "name": "33bcb43e",
            "queries": [
              {
                "name": "main_query",
                "query": {
                  "datasetName": "8daeeada",
                  "fields": [
                    {
                      "name": "count(*)",
                      "expression": "COUNT(`*`)"
                    }
                  ],
                  "disaggregated": false
                }
              }
            ],
            "spec": {
              "version": 2,
              "widgetType": "counter",
              "encodings": {
                "value": {
                  "fieldName": "count(*)",
                  "format": {
                    "type": "number-plain",
                    "abbreviation": "none",
                    "decimalPlaces": {
                      "type": "all"
                    }
                  },
                  "displayName": "Count of Records"
                }
              },
              "frame": {
                "showTitle": true,
                "title": "Total\n"
              }
            }
          },
          "position": {
            "x": 0,
            "y": 0,
            "width": 1,
            "height": 2
          }
        },
        {
          "widget": {
            "name": "2e224dd2",
            "queries": [
              {
                "name": "main_query",
                "query": {
                  "datasetName": "8daeeada",
                  "fields": [
                    {
                      "name": "operationType",
                      "expression": "`operationType`"
                    },
                    {
                      "name": "wallTime",
                      "expression": "`wallTime`"
                    },
                    {
                      "name": "title",
                      "expression": "`title`"
                    },
                    {
                      "name": "_id",
                      "expression": "`_id`"
                    },
                    {
                      "name": "awards",
                      "expression": "`awards`"
                    },
                    {
                      "name": "cast",
                      "expression": "`cast`"
                    },
                    {
                      "name": "countries",
                      "expression": "`countries`"
                    },
                    {
                      "name": "directors",
                      "expression": "`directors`"
                    },
                    {
                      "name": "fullplot",
                      "expression": "`fullplot`"
                    },
                    {
                      "name": "genres",
                      "expression": "`genres`"
                    },
                    {
                      "name": "imdb",
                      "expression": "`imdb`"
                    },
                    {
                      "name": "languages",
                      "expression": "`languages`"
                    },
                    {
                      "name": "lastupdated",
                      "expression": "`lastupdated`"
                    },
                    {
                      "name": "metacritic",
                      "expression": "`metacritic`"
                    },
                    {
                      "name": "num_mflix_comments",
                      "expression": "`num_mflix_comments`"
                    },
                    {
                      "name": "plot",
                      "expression": "`plot`"
                    },
                    {
                      "name": "poster",
                      "expression": "`poster`"
                    },
                    {
                      "name": "rated",
                      "expression": "`rated`"
                    },
                    {
                      "name": "released",
                      "expression": "`released`"
                    },
                    {
                      "name": "runtime",
                      "expression": "`runtime`"
                    },
                    {
                      "name": "tomatoes",
                      "expression": "`tomatoes`"
                    },
                    {
                      "name": "type",
                      "expression": "`type`"
                    },
                    {
                      "name": "writers",
                      "expression": "`writers`"
                    },
                    {
                      "name": "year",
                      "expression": "`year`"
                    },
                    {
                      "name": "coll",
                      "expression": "`coll`"
                    },
                    {
                      "name": "db",
                      "expression": "`db`"
                    }
                  ],
                  "disaggregated": true
                }
              }
            ],
            "spec": {
              "version": 1,
              "widgetType": "table",
              "encodings": {
                "columns": [
                  {
                    "fieldName": "operationType",
                    "booleanValues": [
                      "false",
                      "true"
                    ],
                    "imageUrlTemplate": "{{ @ }}",
                    "imageTitleTemplate": "{{ @ }}",
                    "imageWidth": "",
                    "imageHeight": "",
                    "linkUrlTemplate": "{{ @ }}",
                    "linkTextTemplate": "{{ @ }}",
                    "linkTitleTemplate": "{{ @ }}",
                    "linkOpenInNewTab": true,
                    "type": "string",
                    "displayAs": "string",
                    "visible": true,
                    "order": 0,
                    "title": "operationType",
                    "allowSearch": false,
                    "alignContent": "left",
                    "allowHTML": false,
                    "highlightLinks": false,
                    "useMonospaceFont": false,
                    "preserveWhitespace": false,
                    "displayName": "operationType"
                  },
                  {
                    "fieldName": "wallTime",
                    "dateTimeFormat": "DD/MM/YYYY HH:mm:ss.SSS",
                    "booleanValues": [
                      "false",
                      "true"
                    ],
                    "imageUrlTemplate": "{{ @ }}",
                    "imageTitleTemplate": "{{ @ }}",
                    "imageWidth": "",
                    "imageHeight": "",
                    "linkUrlTemplate": "{{ @ }}",
                    "linkTextTemplate": "{{ @ }}",
                    "linkTitleTemplate": "{{ @ }}",
                    "linkOpenInNewTab": true,
                    "type": "datetime",
                    "displayAs": "datetime",
                    "visible": true,
                    "order": 1,
                    "title": "wallTime",
                    "allowSearch": false,
                    "alignContent": "right",
                    "allowHTML": false,
                    "highlightLinks": false,
                    "useMonospaceFont": false,
                    "preserveWhitespace": false,
                    "displayName": "wallTime"
                  },
                  {
                    "fieldName": "title",
                    "booleanValues": [
                      "false",
                      "true"
                    ],
                    "imageUrlTemplate": "{{ @ }}",
                    "imageTitleTemplate": "{{ @ }}",
                    "imageWidth": "",
                    "imageHeight": "",
                    "linkUrlTemplate": "{{ @ }}",
                    "linkTextTemplate": "{{ @ }}",
                    "linkTitleTemplate": "{{ @ }}",
                    "linkOpenInNewTab": true,
                    "type": "string",
                    "displayAs": "string",
                    "visible": true,
                    "order": 2,
                    "title": "title",
                    "allowSearch": false,
                    "alignContent": "left",
                    "allowHTML": false,
                    "highlightLinks": false,
                    "useMonospaceFont": false,
                    "preserveWhitespace": false,
                    "displayName": "title"
                  },
                  {
                    "fieldName": "_id",
                    "booleanValues": [
                      "false",
                      "true"
                    ],
                    "imageUrlTemplate": "{{ @ }}",
                    "imageTitleTemplate": "{{ @ }}",
                    "imageWidth": "",
                    "imageHeight": "",
                    "linkUrlTemplate": "{{ @ }}",
                    "linkTextTemplate": "{{ @ }}",
                    "linkTitleTemplate": "{{ @ }}",
                    "linkOpenInNewTab": true,
                    "type": "string",
                    "displayAs": "string",
                    "visible": true,
                    "order": 3,
                    "title": "_id",
                    "allowSearch": false,
                    "alignContent": "left",
                    "allowHTML": false,
                    "highlightLinks": false,
                    "useMonospaceFont": false,
                    "preserveWhitespace": false,
                    "displayName": "_id"
                  },
                  {
                    "fieldName": "awards",
                    "booleanValues": [
                      "false",
                      "true"
                    ],
                    "imageUrlTemplate": "{{ @ }}",
                    "imageTitleTemplate": "{{ @ }}",
                    "imageWidth": "",
                    "imageHeight": "",
                    "linkUrlTemplate": "{{ @ }}",
                    "linkTextTemplate": "{{ @ }}",
                    "linkTitleTemplate": "{{ @ }}",
                    "linkOpenInNewTab": true,
                    "type": "complex",
                    "displayAs": "json",
                    "visible": true,
                    "order": 4,
                    "title": "awards",
                    "allowSearch": false,
                    "alignContent": "left",
                    "allowHTML": false,
                    "highlightLinks": false,
                    "useMonospaceFont": false,
                    "preserveWhitespace": false,
                    "displayName": "awards"
                  },
                  {
                    "fieldName": "cast",
                    "booleanValues": [
                      "false",
                      "true"
                    ],
                    "imageUrlTemplate": "{{ @ }}",
                    "imageTitleTemplate": "{{ @ }}",
                    "imageWidth": "",
                    "imageHeight": "",
                    "linkUrlTemplate": "{{ @ }}",
                    "linkTextTemplate": "{{ @ }}",
                    "linkTitleTemplate": "{{ @ }}",
                    "linkOpenInNewTab": true,
                    "type": "complex",
                    "displayAs": "json",
                    "visible": true,
                    "order": 5,
                    "title": "cast",
                    "allowSearch": false,
                    "alignContent": "left",
                    "allowHTML": false,
                    "highlightLinks": false,
                    "useMonospaceFont": false,
                    "preserveWhitespace": false,
                    "displayName": "cast"
                  },
                  {
                    "fieldName": "countries",
                    "booleanValues": [
                      "false",
                      "true"
                    ],
                    "imageUrlTemplate": "{{ @ }}",
                    "imageTitleTemplate": "{{ @ }}",
                    "imageWidth": "",
                    "imageHeight": "",
                    "linkUrlTemplate": "{{ @ }}",
                    "linkTextTemplate": "{{ @ }}",
                    "linkTitleTemplate": "{{ @ }}",
                    "linkOpenInNewTab": true,
                    "type": "complex",
                    "displayAs": "json",
                    "visible": true,
                    "order": 6,
                    "title": "countries",
                    "allowSearch": false,
                    "alignContent": "left",
                    "allowHTML": false,
                    "highlightLinks": false,
                    "useMonospaceFont": false,
                    "preserveWhitespace": false,
                    "displayName": "countries"
                  },
                  {
                    "fieldName": "directors",
                    "booleanValues": [
                      "false",
                      "true"
                    ],
                    "imageUrlTemplate": "{{ @ }}",
                    "imageTitleTemplate": "{{ @ }}",
                    "imageWidth": "",
                    "imageHeight": "",
                    "linkUrlTemplate": "{{ @ }}",
                    "linkTextTemplate": "{{ @ }}",
                    "linkTitleTemplate": "{{ @ }}",
                    "linkOpenInNewTab": true,
                    "type": "complex",
                    "displayAs": "json",
                    "visible": true,
                    "order": 7,
                    "title": "directors",
                    "allowSearch": false,
                    "alignContent": "left",
                    "allowHTML": false,
                    "highlightLinks": false,
                    "useMonospaceFont": false,
                    "preserveWhitespace": false,
                    "displayName": "directors"
                  },
                  {
                    "fieldName": "fullplot",
                    "booleanValues": [
                      "false",
                      "true"
                    ],
                    "imageUrlTemplate": "{{ @ }}",
                    "imageTitleTemplate": "{{ @ }}",
                    "imageWidth": "",
                    "imageHeight": "",
                    "linkUrlTemplate": "{{ @ }}",
                    "linkTextTemplate": "{{ @ }}",
                    "linkTitleTemplate": "{{ @ }}",
                    "linkOpenInNewTab": true,
                    "type": "string",
                    "displayAs": "string",
                    "visible": true,
                    "order": 8,
                    "title": "fullplot",
                    "allowSearch": false,
                    "alignContent": "left",
                    "allowHTML": false,
                    "highlightLinks": false,
                    "useMonospaceFont": false,
                    "preserveWhitespace": false,
                    "displayName": "fullplot"
                  },
                  {
                    "fieldName": "genres",
                    "booleanValues": [
                      "false",
                      "true"
                    ],
                    "imageUrlTemplate": "{{ @ }}",
                    "imageTitleTemplate": "{{ @ }}",
                    "imageWidth": "",
                    "imageHeight": "",
                    "linkUrlTemplate": "{{ @ }}",
                    "linkTextTemplate": "{{ @ }}",
                    "linkTitleTemplate": "{{ @ }}",
                    "linkOpenInNewTab": true,
                    "type": "complex",
                    "displayAs": "json",
                    "visible": true,
                    "order": 9,
                    "title": "genres",
                    "allowSearch": false,
                    "alignContent": "left",
                    "allowHTML": false,
                    "highlightLinks": false,
                    "useMonospaceFont": false,
                    "preserveWhitespace": false,
                    "displayName": "genres"
                  },
                  {
                    "fieldName": "imdb",
                    "booleanValues": [
                      "false",
                      "true"
                    ],
                    "imageUrlTemplate": "{{ @ }}",
                    "imageTitleTemplate": "{{ @ }}",
                    "imageWidth": "",
                    "imageHeight": "",
                    "linkUrlTemplate": "{{ @ }}",
                    "linkTextTemplate": "{{ @ }}",
                    "linkTitleTemplate": "{{ @ }}",
                    "linkOpenInNewTab": true,
                    "type": "complex",
                    "displayAs": "json",
                    "visible": true,
                    "order": 10,
                    "title": "imdb",
                    "allowSearch": false,
                    "alignContent": "left",
                    "allowHTML": false,
                    "highlightLinks": false,
                    "useMonospaceFont": false,
                    "preserveWhitespace": false,
                    "displayName": "imdb"
                  },
                  {
                    "fieldName": "languages",
                    "booleanValues": [
                      "false",
                      "true"
                    ],
                    "imageUrlTemplate": "{{ @ }}",
                    "imageTitleTemplate": "{{ @ }}",
                    "imageWidth": "",
                    "imageHeight": "",
                    "linkUrlTemplate": "{{ @ }}",
                    "linkTextTemplate": "{{ @ }}",
                    "linkTitleTemplate": "{{ @ }}",
                    "linkOpenInNewTab": true,
                    "type": "complex",
                    "displayAs": "json",
                    "visible": true,
                    "order": 11,
                    "title": "languages",
                    "allowSearch": false,
                    "alignContent": "left",
                    "allowHTML": false,
                    "highlightLinks": false,
                    "useMonospaceFont": false,
                    "preserveWhitespace": false,
                    "displayName": "languages"
                  },
                  {
                    "fieldName": "lastupdated",
                    "booleanValues": [
                      "false",
                      "true"
                    ],
                    "imageUrlTemplate": "{{ @ }}",
                    "imageTitleTemplate": "{{ @ }}",
                    "imageWidth": "",
                    "imageHeight": "",
                    "linkUrlTemplate": "{{ @ }}",
                    "linkTextTemplate": "{{ @ }}",
                    "linkTitleTemplate": "{{ @ }}",
                    "linkOpenInNewTab": true,
                    "type": "string",
                    "displayAs": "string",
                    "visible": true,
                    "order": 12,
                    "title": "lastupdated",
                    "allowSearch": false,
                    "alignContent": "left",
                    "allowHTML": false,
                    "highlightLinks": false,
                    "useMonospaceFont": false,
                    "preserveWhitespace": false,
                    "displayName": "lastupdated"
                  },
                  {
                    "fieldName": "metacritic",
                    "numberFormat": "0",
                    "booleanValues": [
                      "false",
                      "true"
                    ],
                    "imageUrlTemplate": "{{ @ }}",
                    "imageTitleTemplate": "{{ @ }}",
                    "imageWidth": "",
                    "imageHeight": "",
                    "linkUrlTemplate": "{{ @ }}",
                    "linkTextTemplate": "{{ @ }}",
                    "linkTitleTemplate": "{{ @ }}",
                    "linkOpenInNewTab": true,
                    "type": "integer",
                    "displayAs": "number",
                    "visible": true,
                    "order": 13,
                    "title": "metacritic",
                    "allowSearch": false,
                    "alignContent": "right",
                    "allowHTML": false,
                    "highlightLinks": false,
                    "useMonospaceFont": false,
                    "preserveWhitespace": false,
                    "displayName": "metacritic"
                  },
                  {
                    "fieldName": "num_mflix_comments",
                    "numberFormat": "0",
                    "booleanValues": [
                      "false",
                      "true"
                    ],
                    "imageUrlTemplate": "{{ @ }}",
                    "imageTitleTemplate": "{{ @ }}",
                    "imageWidth": "",
                    "imageHeight": "",
                    "linkUrlTemplate": "{{ @ }}",
                    "linkTextTemplate": "{{ @ }}",
                    "linkTitleTemplate": "{{ @ }}",
                    "linkOpenInNewTab": true,
                    "type": "integer",
                    "displayAs": "number",
                    "visible": true,
                    "order": 14,
                    "title": "num_mflix_comments",
                    "allowSearch": false,
                    "alignContent": "right",
                    "allowHTML": false,
                    "highlightLinks": false,
                    "useMonospaceFont": false,
                    "preserveWhitespace": false,
                    "displayName": "num_mflix_comments"
                  },
                  {
                    "fieldName": "plot",
                    "booleanValues": [
                      "false",
                      "true"
                    ],
                    "imageUrlTemplate": "{{ @ }}",
                    "imageTitleTemplate": "{{ @ }}",
                    "imageWidth": "",
                    "imageHeight": "",
                    "linkUrlTemplate": "{{ @ }}",
                    "linkTextTemplate": "{{ @ }}",
                    "linkTitleTemplate": "{{ @ }}",
                    "linkOpenInNewTab": true,
                    "type": "string",
                    "displayAs": "string",
                    "visible": true,
                    "order": 15,
                    "title": "plot",
                    "allowSearch": false,
                    "alignContent": "left",
                    "allowHTML": false,
                    "highlightLinks": false,
                    "useMonospaceFont": false,
                    "preserveWhitespace": false,
                    "displayName": "plot"
                  },
                  {
                    "fieldName": "poster",
                    "booleanValues": [
                      "false",
                      "true"
                    ],
                    "imageUrlTemplate": "{{ @ }}",
                    "imageTitleTemplate": "{{ @ }}",
                    "imageWidth": "",
                    "imageHeight": "",
                    "linkUrlTemplate": "{{ @ }}",
                    "linkTextTemplate": "{{ @ }}",
                    "linkTitleTemplate": "{{ @ }}",
                    "linkOpenInNewTab": true,
                    "type": "string",
                    "displayAs": "string",
                    "visible": true,
                    "order": 16,
                    "title": "poster",
                    "allowSearch": false,
                    "alignContent": "left",
                    "allowHTML": false,
                    "highlightLinks": false,
                    "useMonospaceFont": false,
                    "preserveWhitespace": false,
                    "displayName": "poster"
                  },
                  {
                    "fieldName": "rated",
                    "booleanValues": [
                      "false",
                      "true"
                    ],
                    "imageUrlTemplate": "{{ @ }}",
                    "imageTitleTemplate": "{{ @ }}",
                    "imageWidth": "",
                    "imageHeight": "",
                    "linkUrlTemplate": "{{ @ }}",
                    "linkTextTemplate": "{{ @ }}",
                    "linkTitleTemplate": "{{ @ }}",
                    "linkOpenInNewTab": true,
                    "type": "string",
                    "displayAs": "string",
                    "visible": true,
                    "order": 17,
                    "title": "rated",
                    "allowSearch": false,
                    "alignContent": "left",
                    "allowHTML": false,
                    "highlightLinks": false,
                    "useMonospaceFont": false,
                    "preserveWhitespace": false,
                    "displayName": "rated"
                  },
                  {
                    "fieldName": "released",
                    "dateTimeFormat": "DD/MM/YYYY HH:mm:ss.SSS",
                    "booleanValues": [
                      "false",
                      "true"
                    ],
                    "imageUrlTemplate": "{{ @ }}",
                    "imageTitleTemplate": "{{ @ }}",
                    "imageWidth": "",
                    "imageHeight": "",
                    "linkUrlTemplate": "{{ @ }}",
                    "linkTextTemplate": "{{ @ }}",
                    "linkTitleTemplate": "{{ @ }}",
                    "linkOpenInNewTab": true,
                    "type": "datetime",
                    "displayAs": "datetime",
                    "visible": true,
                    "order": 18,
                    "title": "released",
                    "allowSearch": false,
                    "alignContent": "right",
                    "allowHTML": false,
                    "highlightLinks": false,
                    "useMonospaceFont": false,
                    "preserveWhitespace": false,
                    "displayName": "released"
                  },
                  {
                    "fieldName": "runtime",
                    "numberFormat": "0",
                    "booleanValues": [
                      "false",
                      "true"
                    ],
                    "imageUrlTemplate": "{{ @ }}",
                    "imageTitleTemplate": "{{ @ }}",
                    "imageWidth": "",
                    "imageHeight": "",
                    "linkUrlTemplate": "{{ @ }}",
                    "linkTextTemplate": "{{ @ }}",
                    "linkTitleTemplate": "{{ @ }}",
                    "linkOpenInNewTab": true,
                    "type": "integer",
                    "displayAs": "number",
                    "visible": true,
                    "order": 19,
                    "title": "runtime",
                    "allowSearch": false,
                    "alignContent": "right",
                    "allowHTML": false,
                    "highlightLinks": false,
                    "useMonospaceFont": false,
                    "preserveWhitespace": false,
                    "displayName": "runtime"
                  },
                  {
                    "fieldName": "tomatoes",
                    "booleanValues": [
                      "false",
                      "true"
                    ],
                    "imageUrlTemplate": "{{ @ }}",
                    "imageTitleTemplate": "{{ @ }}",
                    "imageWidth": "",
                    "imageHeight": "",
                    "linkUrlTemplate": "{{ @ }}",
                    "linkTextTemplate": "{{ @ }}",
                    "linkTitleTemplate": "{{ @ }}",
                    "linkOpenInNewTab": true,
                    "type": "complex",
                    "displayAs": "json",
                    "visible": true,
                    "order": 20,
                    "title": "tomatoes",
                    "allowSearch": false,
                    "alignContent": "left",
                    "allowHTML": false,
                    "highlightLinks": false,
                    "useMonospaceFont": false,
                    "preserveWhitespace": false,
                    "displayName": "tomatoes"
                  },
                  {
                    "fieldName": "type",
                    "booleanValues": [
                      "false",
                      "true"
                    ],
                    "imageUrlTemplate": "{{ @ }}",
                    "imageTitleTemplate": "{{ @ }}",
                    "imageWidth": "",
                    "imageHeight": "",
                    "linkUrlTemplate": "{{ @ }}",
                    "linkTextTemplate": "{{ @ }}",
                    "linkTitleTemplate": "{{ @ }}",
                    "linkOpenInNewTab": true,
                    "type": "string",
                    "displayAs": "string",
                    "visible": true,
                    "order": 21,
                    "title": "type",
                    "allowSearch": false,
                    "alignContent": "left",
                    "allowHTML": false,
                    "highlightLinks": false,
                    "useMonospaceFont": false,
                    "preserveWhitespace": false,
                    "displayName": "type"
                  },
                  {
                    "fieldName": "writers",
                    "booleanValues": [
                      "false",
                      "true"
                    ],
                    "imageUrlTemplate": "{{ @ }}",
                    "imageTitleTemplate": "{{ @ }}",
                    "imageWidth": "",
                    "imageHeight": "",
                    "linkUrlTemplate": "{{ @ }}",
                    "linkTextTemplate": "{{ @ }}",
                    "linkTitleTemplate": "{{ @ }}",
                    "linkOpenInNewTab": true,
                    "type": "complex",
                    "displayAs": "json",
                    "visible": true,
                    "order": 22,
                    "title": "writers",
                    "allowSearch": false,
                    "alignContent": "left",
                    "allowHTML": false,
                    "highlightLinks": false,
                    "useMonospaceFont": false,
                    "preserveWhitespace": false,
                    "displayName": "writers"
                  },
                  {
                    "fieldName": "year",
                    "booleanValues": [
                      "false",
                      "true"
                    ],
                    "imageUrlTemplate": "{{ @ }}",
                    "imageTitleTemplate": "{{ @ }}",
                    "imageWidth": "",
                    "imageHeight": "",
                    "linkUrlTemplate": "{{ @ }}",
                    "linkTextTemplate": "{{ @ }}",
                    "linkTitleTemplate": "{{ @ }}",
                    "linkOpenInNewTab": true,
                    "type": "string",
                    "displayAs": "string",
                    "visible": true,
                    "order": 23,
                    "title": "year",
                    "allowSearch": false,
                    "alignContent": "left",
                    "allowHTML": false,
                    "highlightLinks": false,
                    "useMonospaceFont": false,
                    "preserveWhitespace": false,
                    "displayName": "year"
                  },
                  {
                    "fieldName": "coll",
                    "booleanValues": [
                      "false",
                      "true"
                    ],
                    "imageUrlTemplate": "{{ @ }}",
                    "imageTitleTemplate": "{{ @ }}",
                    "imageWidth": "",
                    "imageHeight": "",
                    "linkUrlTemplate": "{{ @ }}",
                    "linkTextTemplate": "{{ @ }}",
                    "linkTitleTemplate": "{{ @ }}",
                    "linkOpenInNewTab": true,
                    "type": "string",
                    "displayAs": "string",
                    "visible": true,
                    "order": 24,
                    "title": "coll",
                    "allowSearch": false,
                    "alignContent": "left",
                    "allowHTML": false,
                    "highlightLinks": false,
                    "useMonospaceFont": false,
                    "preserveWhitespace": false,
                    "displayName": "coll"
                  },
                  {
                    "fieldName": "db",
                    "booleanValues": [
                      "false",
                      "true"
                    ],
                    "imageUrlTemplate": "{{ @ }}",
                    "imageTitleTemplate": "{{ @ }}",
                    "imageWidth": "",
                    "imageHeight": "",
                    "linkUrlTemplate": "{{ @ }}",
                    "linkTextTemplate": "{{ @ }}",
                    "linkTitleTemplate": "{{ @ }}",
                    "linkOpenInNewTab": true,
                    "type": "string",
                    "displayAs": "string",
                    "visible": true,
                    "order": 25,
                    "title": "db",
                    "allowSearch": false,
                    "alignContent": "left",
                    "allowHTML": false,
                    "highlightLinks": false,
                    "useMonospaceFont": false,
                    "preserveWhitespace": false,
                    "displayName": "db"
                  }
                ]
              },
              "invisibleColumns": [],
              "allowHTMLByDefault": false,
              "itemsPerPage": 25,
              "paginationSize": "default",
              "condensed": true,
              "withRowNumber": false
            }
          },
          "position": {
            "x": 0,
            "y": 2,
            "width": 5,
            "height": 7
          }
        },
        {
          "widget": {
            "name": "00fb0f6b",
            "queries": [
              {
                "name": "main_query",
                "query": {
                  "datasetName": "dataset1",
                  "fields": [
                    {
                      "name": "operationType",
                      "expression": "`operationType`"
                    }
                  ],
                  "filters": [
                    {
                      "expression": "`operationType` IN ('insert')"
                    }
                  ],
                  "disaggregated": true
                }
              }
            ],
            "spec": {
              "version": 2,
              "widgetType": "counter",
              "encodings": {
                "value": {
                  "fieldName": "operationType",
                  "displayName": "operationType"
                }
              }
            }
          },
          "position": {
            "x": 1,
            "y": 0,
            "width": 2,
            "height": 2
          }
        },
        {
          "widget": {
            "name": "355d466d",
            "queries": [
              {
                "name": "main_query",
                "query": {
                  "datasetName": "dataset1",
                  "fields": [
                    {
                      "name": "operationType",
                      "expression": "`operationType`"
                    },
                    {
                      "name": "id",
                      "expression": "`id`"
                    },
                    {
                      "name": "wallTime",
                      "expression": "`wallTime`"
                    },
                    {
                      "name": "title",
                      "expression": "`title`"
                    },
                    {
                      "name": "genres",
                      "expression": "`genres`"
                    },
                    {
                      "name": "year",
                      "expression": "`year`"
                    },
                    {
                      "name": "source",
                      "expression": "`source`"
                    }
                  ],
                  "filters": [
                    {
                      "expression": "`operationType` IS NULL OR `operationType` NOT IN ('insert')"
                    }
                  ],
                  "disaggregated": true
                }
              }
            ],
            "spec": {
              "version": 1,
              "widgetType": "table",
              "encodings": {
                "columns": [
                  {
                    "fieldName": "operationType",
                    "booleanValues": [
                      "false",
                      "true"
                    ],
                    "imageUrlTemplate": "{{ @ }}",
                    "imageTitleTemplate": "{{ @ }}",
                    "imageWidth": "",
                    "imageHeight": "",
                    "linkUrlTemplate": "{{ @ }}",
                    "linkTextTemplate": "{{ @ }}",
                    "linkTitleTemplate": "{{ @ }}",
                    "linkOpenInNewTab": true,
                    "type": "string",
                    "displayAs": "string",
                    "visible": true,
                    "order": 0,
                    "title": "operationType",
                    "allowSearch": false,
                    "alignContent": "left",
                    "allowHTML": false,
                    "highlightLinks": false,
                    "useMonospaceFont": false,
                    "preserveWhitespace": false,
                    "displayName": "operationType"
                  },
                  {
                    "fieldName": "id",
                    "booleanValues": [
                      "false",
                      "true"
                    ],
                    "imageUrlTemplate": "{{ @ }}",
                    "imageTitleTemplate": "{{ @ }}",
                    "imageWidth": "",
                    "imageHeight": "",
                    "linkUrlTemplate": "{{ @ }}",
                    "linkTextTemplate": "{{ @ }}",
                    "linkTitleTemplate": "{{ @ }}",
                    "linkOpenInNewTab": true,
                    "type": "string",
                    "displayAs": "string",
                    "visible": true,
                    "order": 1,
                    "title": "id",
                    "allowSearch": false,
                    "alignContent": "left",
                    "allowHTML": false,
                    "highlightLinks": false,
                    "useMonospaceFont": false,
                    "preserveWhitespace": false,
                    "displayName": "id"
                  },
                  {
                    "fieldName": "wallTime",
                    "dateTimeFormat": "DD/MM/YYYY HH:mm:ss.SSS",
                    "booleanValues": [
                      "false",
                      "true"
                    ],
                    "imageUrlTemplate": "{{ @ }}",
                    "imageTitleTemplate": "{{ @ }}",
                    "imageWidth": "",
                    "imageHeight": "",
                    "linkUrlTemplate": "{{ @ }}",
                    "linkTextTemplate": "{{ @ }}",
                    "linkTitleTemplate": "{{ @ }}",
                    "linkOpenInNewTab": true,
                    "type": "datetime",
                    "displayAs": "datetime",
                    "visible": true,
                    "order": 2,
                    "title": "wallTime",
                    "allowSearch": false,
                    "alignContent": "right",
                    "allowHTML": false,
                    "highlightLinks": false,
                    "useMonospaceFont": false,
                    "preserveWhitespace": false,
                    "displayName": "wallTime"
                  },
                  {
                    "fieldName": "title",
                    "booleanValues": [
                      "false",
                      "true"
                    ],
                    "imageUrlTemplate": "{{ @ }}",
                    "imageTitleTemplate": "{{ @ }}",
                    "imageWidth": "",
                    "imageHeight": "",
                    "linkUrlTemplate": "{{ @ }}",
                    "linkTextTemplate": "{{ @ }}",
                    "linkTitleTemplate": "{{ @ }}",
                    "linkOpenInNewTab": true,
                    "type": "string",
                    "displayAs": "string",
                    "visible": true,
                    "order": 3,
                    "title": "title",
                    "allowSearch": false,
                    "alignContent": "left",
                    "allowHTML": false,
                    "highlightLinks": false,
                    "useMonospaceFont": false,
                    "preserveWhitespace": false,
                    "displayName": "title"
                  },
                  {
                    "fieldName": "genres",
                    "booleanValues": [
                      "false",
                      "true"
                    ],
                    "imageUrlTemplate": "{{ @ }}",
                    "imageTitleTemplate": "{{ @ }}",
                    "imageWidth": "",
                    "imageHeight": "",
                    "linkUrlTemplate": "{{ @ }}",
                    "linkTextTemplate": "{{ @ }}",
                    "linkTitleTemplate": "{{ @ }}",
                    "linkOpenInNewTab": true,
                    "type": "complex",
                    "displayAs": "json",
                    "visible": true,
                    "order": 4,
                    "title": "genres",
                    "allowSearch": false,
                    "alignContent": "left",
                    "allowHTML": false,
                    "highlightLinks": false,
                    "useMonospaceFont": false,
                    "preserveWhitespace": false,
                    "displayName": "genres"
                  },
                  {
                    "fieldName": "year",
                    "booleanValues": [
                      "false",
                      "true"
                    ],
                    "imageUrlTemplate": "{{ @ }}",
                    "imageTitleTemplate": "{{ @ }}",
                    "imageWidth": "",
                    "imageHeight": "",
                    "linkUrlTemplate": "{{ @ }}",
                    "linkTextTemplate": "{{ @ }}",
                    "linkTitleTemplate": "{{ @ }}",
                    "linkOpenInNewTab": true,
                    "type": "string",
                    "displayAs": "string",
                    "visible": true,
                    "order": 5,
                    "title": "year",
                    "allowSearch": false,
                    "alignContent": "left",
                    "allowHTML": false,
                    "highlightLinks": false,
                    "useMonospaceFont": false,
                    "preserveWhitespace": false,
                    "displayName": "year"
                  },
                  {
                    "fieldName": "source",
                    "booleanValues": [
                      "false",
                      "true"
                    ],
                    "imageUrlTemplate": "{{ @ }}",
                    "imageTitleTemplate": "{{ @ }}",
                    "imageWidth": "",
                    "imageHeight": "",
                    "linkUrlTemplate": "{{ @ }}",
                    "linkTextTemplate": "{{ @ }}",
                    "linkTitleTemplate": "{{ @ }}",
                    "linkOpenInNewTab": true,
                    "type": "string",
                    "displayAs": "string",
                    "visible": true,
                    "order": 6,
                    "title": "source",
                    "allowSearch": false,
                    "alignContent": "left",
                    "allowHTML": false,
                    "highlightLinks": false,
                    "useMonospaceFont": false,
                    "preserveWhitespace": false,
                    "displayName": "source"
                  }
                ]
              },
              "invisibleColumns": [],
              "allowHTMLByDefault": false,
              "itemsPerPage": 25,
              "paginationSize": "default",
              "condensed": true,
              "withRowNumber": false,
              "frame": {
                "title": "Table of deleted movies",
                "showTitle": true
              }
            }
          },
          "position": {
            "x": 0,
            "y": 9,
            "width": 3,
            "height": 6
          }
        }
      ],
      "pageType": "PAGE_TYPE_CANVAS"
    },
    {
      "name": "e73ccac0",
      "displayName": "Bronze - imdb",
      "layout": [
        {
          "widget": {
            "name": "7d288d37",
            "queries": [
              {
                "name": "main_query",
                "query": {
                  "datasetName": "d04ce6d0",
                  "fields": [
                    {
                      "name": "count(*)",
                      "expression": "COUNT(`*`)"
                    }
                  ],
                  "disaggregated": false
                }
              }
            ],
            "spec": {
              "version": 2,
              "widgetType": "counter",
              "encodings": {
                "value": {
                  "fieldName": "count(*)",
                  "format": {
                    "type": "number-plain",
                    "abbreviation": "none",
                    "decimalPlaces": {
                      "type": "max",
                      "places": 2
                    }
                  },
                  "displayName": "Count of Records"
                }
              }
            }
          },
          "position": {
            "x": 0,
            "y": 0,
            "width": 1,
            "height": 2
          }
        },
        {
          "widget": {
            "name": "3220c03e",
            "queries": [
              {
                "name": "main_query",
                "query": {
                  "datasetName": "d04ce6d0",
                  "fields": [
                    {
                      "name": "wallTime",
                      "expression": "`wallTime`"
                    },
                    {
                      "name": "primaryTitle",
                      "expression": "`primaryTitle`"
                    },
                    {
                      "name": "genres",
                      "expression": "`genres`"
                    },
                    {
                      "name": "tconst",
                      "expression": "`tconst`"
                    },
                    {
                      "name": "titleType",
                      "expression": "`titleType`"
                    },
                    {
                      "name": "originalTitle",
                      "expression": "`originalTitle`"
                    },
                    {
                      "name": "isAdult",
                      "expression": "`isAdult`"
                    },
                    {
                      "name": "startYear",
                      "expression": "`startYear`"
                    },
                    {
                      "name": "endYear",
                      "expression": "`endYear`"
                    },
                    {
                      "name": "runtimeMinutes",
                      "expression": "`runtimeMinutes`"
                    },
                    {
                      "name": "_rescued_data",
                      "expression": "`_rescued_data`"
                    }
                  ],
                  "disaggregated": true
                }
              }
            ],
            "spec": {
              "version": 1,
              "widgetType": "table",
              "encodings": {
                "columns": [
                  {
                    "fieldName": "wallTime",
                    "dateTimeFormat": "DD/MM/YYYY HH:mm:ss.SSS",
                    "booleanValues": [
                      "false",
                      "true"
                    ],
                    "imageUrlTemplate": "{{ @ }}",
                    "imageTitleTemplate": "{{ @ }}",
                    "imageWidth": "",
                    "imageHeight": "",
                    "linkUrlTemplate": "{{ @ }}",
                    "linkTextTemplate": "{{ @ }}",
                    "linkTitleTemplate": "{{ @ }}",
                    "linkOpenInNewTab": true,
                    "type": "datetime",
                    "displayAs": "datetime",
                    "visible": true,
                    "order": 0,
                    "title": "wallTime",
                    "allowSearch": false,
                    "alignContent": "right",
                    "allowHTML": false,
                    "highlightLinks": false,
                    "useMonospaceFont": false,
                    "preserveWhitespace": false,
                    "displayName": "wallTime"
                  },
                  {
                    "fieldName": "primaryTitle",
                    "booleanValues": [
                      "false",
                      "true"
                    ],
                    "imageUrlTemplate": "{{ @ }}",
                    "imageTitleTemplate": "{{ @ }}",
                    "imageWidth": "",
                    "imageHeight": "",
                    "linkUrlTemplate": "{{ @ }}",
                    "linkTextTemplate": "{{ @ }}",
                    "linkTitleTemplate": "{{ @ }}",
                    "linkOpenInNewTab": true,
                    "type": "string",
                    "displayAs": "string",
                    "visible": true,
                    "order": 1,
                    "title": "primaryTitle",
                    "allowSearch": false,
                    "alignContent": "left",
                    "allowHTML": false,
                    "highlightLinks": false,
                    "useMonospaceFont": false,
                    "preserveWhitespace": false,
                    "displayName": "primaryTitle"
                  },
                  {
                    "fieldName": "genres",
                    "booleanValues": [
                      "false",
                      "true"
                    ],
                    "imageUrlTemplate": "{{ @ }}",
                    "imageTitleTemplate": "{{ @ }}",
                    "imageWidth": "",
                    "imageHeight": "",
                    "linkUrlTemplate": "{{ @ }}",
                    "linkTextTemplate": "{{ @ }}",
                    "linkTitleTemplate": "{{ @ }}",
                    "linkOpenInNewTab": true,
                    "type": "string",
                    "displayAs": "json",
                    "visible": true,
                    "order": 2,
                    "title": "genres",
                    "allowSearch": false,
                    "alignContent": "left",
                    "allowHTML": false,
                    "highlightLinks": false,
                    "useMonospaceFont": false,
                    "preserveWhitespace": false,
                    "displayName": "genres"
                  },
                  {
                    "fieldName": "tconst",
                    "booleanValues": [
                      "false",
                      "true"
                    ],
                    "imageUrlTemplate": "{{ @ }}",
                    "imageTitleTemplate": "{{ @ }}",
                    "imageWidth": "",
                    "imageHeight": "",
                    "linkUrlTemplate": "{{ @ }}",
                    "linkTextTemplate": "{{ @ }}",
                    "linkTitleTemplate": "{{ @ }}",
                    "linkOpenInNewTab": true,
                    "type": "string",
                    "displayAs": "string",
                    "visible": true,
                    "order": 3,
                    "title": "tconst",
                    "allowSearch": false,
                    "alignContent": "left",
                    "allowHTML": false,
                    "highlightLinks": false,
                    "useMonospaceFont": false,
                    "preserveWhitespace": false,
                    "displayName": "tconst"
                  },
                  {
                    "fieldName": "titleType",
                    "booleanValues": [
                      "false",
                      "true"
                    ],
                    "imageUrlTemplate": "{{ @ }}",
                    "imageTitleTemplate": "{{ @ }}",
                    "imageWidth": "",
                    "imageHeight": "",
                    "linkUrlTemplate": "{{ @ }}",
                    "linkTextTemplate": "{{ @ }}",
                    "linkTitleTemplate": "{{ @ }}",
                    "linkOpenInNewTab": true,
                    "type": "string",
                    "displayAs": "string",
                    "visible": true,
                    "order": 4,
                    "title": "titleType",
                    "allowSearch": false,
                    "alignContent": "left",
                    "allowHTML": false,
                    "highlightLinks": false,
                    "useMonospaceFont": false,
                    "preserveWhitespace": false,
                    "displayName": "titleType"
                  },
                  {
                    "fieldName": "originalTitle",
                    "booleanValues": [
                      "false",
                      "true"
                    ],
                    "imageUrlTemplate": "{{ @ }}",
                    "imageTitleTemplate": "{{ @ }}",
                    "imageWidth": "",
                    "imageHeight": "",
                    "linkUrlTemplate": "{{ @ }}",
                    "linkTextTemplate": "{{ @ }}",
                    "linkTitleTemplate": "{{ @ }}",
                    "linkOpenInNewTab": true,
                    "type": "string",
                    "displayAs": "string",
                    "visible": true,
                    "order": 5,
                    "title": "originalTitle",
                    "allowSearch": false,
                    "alignContent": "left",
                    "allowHTML": false,
                    "highlightLinks": false,
                    "useMonospaceFont": false,
                    "preserveWhitespace": false,
                    "displayName": "originalTitle"
                  },
                  {
                    "fieldName": "isAdult",
                    "numberFormat": "0",
                    "booleanValues": [
                      "false",
                      "true"
                    ],
                    "imageUrlTemplate": "{{ @ }}",
                    "imageTitleTemplate": "{{ @ }}",
                    "imageWidth": "",
                    "imageHeight": "",
                    "linkUrlTemplate": "{{ @ }}",
                    "linkTextTemplate": "{{ @ }}",
                    "linkTitleTemplate": "{{ @ }}",
                    "linkOpenInNewTab": true,
                    "type": "integer",
                    "displayAs": "number",
                    "visible": true,
                    "order": 6,
                    "title": "isAdult",
                    "allowSearch": false,
                    "alignContent": "right",
                    "allowHTML": false,
                    "highlightLinks": false,
                    "useMonospaceFont": false,
                    "preserveWhitespace": false,
                    "displayName": "isAdult"
                  },
                  {
                    "fieldName": "startYear",
                    "booleanValues": [
                      "false",
                      "true"
                    ],
                    "imageUrlTemplate": "{{ @ }}",
                    "imageTitleTemplate": "{{ @ }}",
                    "imageWidth": "",
                    "imageHeight": "",
                    "linkUrlTemplate": "{{ @ }}",
                    "linkTextTemplate": "{{ @ }}",
                    "linkTitleTemplate": "{{ @ }}",
                    "linkOpenInNewTab": true,
                    "type": "string",
                    "displayAs": "string",
                    "visible": true,
                    "order": 7,
                    "title": "startYear",
                    "allowSearch": false,
                    "alignContent": "left",
                    "allowHTML": false,
                    "highlightLinks": false,
                    "useMonospaceFont": false,
                    "preserveWhitespace": false,
                    "displayName": "startYear"
                  },
                  {
                    "fieldName": "endYear",
                    "booleanValues": [
                      "false",
                      "true"
                    ],
                    "imageUrlTemplate": "{{ @ }}",
                    "imageTitleTemplate": "{{ @ }}",
                    "imageWidth": "",
                    "imageHeight": "",
                    "linkUrlTemplate": "{{ @ }}",
                    "linkTextTemplate": "{{ @ }}",
                    "linkTitleTemplate": "{{ @ }}",
                    "linkOpenInNewTab": true,
                    "type": "string",
                    "displayAs": "string",
                    "visible": true,
                    "order": 8,
                    "title": "endYear",
                    "allowSearch": false,
                    "alignContent": "left",
                    "allowHTML": false,
                    "highlightLinks": false,
                    "useMonospaceFont": false,
                    "preserveWhitespace": false,
                    "displayName": "endYear"
                  },
                  {
                    "fieldName": "runtimeMinutes",
                    "booleanValues": [
                      "false",
                      "true"
                    ],
                    "imageUrlTemplate": "{{ @ }}",
                    "imageTitleTemplate": "{{ @ }}",
                    "imageWidth": "",
                    "imageHeight": "",
                    "linkUrlTemplate": "{{ @ }}",
                    "linkTextTemplate": "{{ @ }}",
                    "linkTitleTemplate": "{{ @ }}",
                    "linkOpenInNewTab": true,
                    "type": "string",
                    "displayAs": "string",
                    "visible": true,
                    "order": 9,
                    "title": "runtimeMinutes",
                    "allowSearch": false,
                    "alignContent": "left",
                    "allowHTML": false,
                    "highlightLinks": false,
                    "useMonospaceFont": false,
                    "preserveWhitespace": false,
                    "displayName": "runtimeMinutes"
                  },
                  {
                    "fieldName": "_rescued_data",
                    "booleanValues": [
                      "false",
                      "true"
                    ],
                    "imageUrlTemplate": "{{ @ }}",
                    "imageTitleTemplate": "{{ @ }}",
                    "imageWidth": "",
                    "imageHeight": "",
                    "linkUrlTemplate": "{{ @ }}",
                    "linkTextTemplate": "{{ @ }}",
                    "linkTitleTemplate": "{{ @ }}",
                    "linkOpenInNewTab": true,
                    "type": "string",
                    "displayAs": "string",
                    "visible": true,
                    "order": 10,
                    "title": "_rescued_data",
                    "allowSearch": false,
                    "alignContent": "left",
                    "allowHTML": false,
                    "highlightLinks": false,
                    "useMonospaceFont": false,
                    "preserveWhitespace": false,
                    "displayName": "_rescued_data"
                  }
                ]
              },
              "invisibleColumns": [],
              "allowHTMLByDefault": false,
              "itemsPerPage": 25,
              "paginationSize": "default",
              "condensed": true,
              "withRowNumber": false
            }
          },
          "position": {
            "x": 0,
            "y": 2,
            "width": 5,
            "height": 7
          }
        }
      ],
      "pageType": "PAGE_TYPE_CANVAS"
    }
  ],
  "uiSettings": {
    "theme": {
      "widgetHeaderAlignment": "ALIGNMENT_UNSPECIFIED"
    }
  }
}
